{"v":"5.7.4","fr":25,"ip":0,"op":200,"w":1920,"h":1080,"nm":"Pre-comp 1","ddd":0,"assets":[{"id":"comp_0","layers":[{"ddd":0,"ind":1,"ty":4,"nm":"“图层 3”轮廓","sr":1,"ks":{"o":{"a":0,"k":100,"ix":11},"r":{"a":0,"k":0,"ix":10},"p":{"a":0,"k":[628.21,508.352,0],"ix":2,"l":2},"a":{"a":0,"k":[-0.422,8.754,0],"ix":1,"l":2},"s":{"a":1,"k":[{"i":{"x":[0.286,0.667,0.667],"y":[1,1,1]},"o":{"x":[0.714,0.333,0.333],"y":[0,0,0]},"t":10.01,"s":[0,100,100]},{"t":20.8541875208542,"s":[100,100,100]}],"ix":6,"l":2}},"ao":0,"shapes":[{"ty":"gr","it":[{"ind":0,"ty":"sh","ix":1,"ks":{"a":0,"k":{"i":[[0,0],[0,0],[0,0],[0,0]],"o":[[0,0],[0,0],[0,0],[0,0]],"v":[[20.828,8.504],[-20.828,8.504],[-20.828,-8.504],[20.828,-8.504]],"c":true},"ix":2},"nm":"路径 1","mn":"ADBE Vector Shape - Group","hd":false},{"ty":"fl","c":{"a":0,"k":[0.092948442347,0.468252413881,1,1],"ix":4},"o":{"a":0,"k":100,"ix":5},"r":1,"bm":0,"nm":"填充 1","mn":"ADBE Vector Graphic - Fill","hd":false},{"ty":"tr","p":{"a":0,"k":[21.078,8.754],"ix":2},"a":{"a":0,"k":[0,0],"ix":1},"s":{"a":0,"k":[100,100],"ix":3},"r":{"a":0,"k":0,"ix":6},"o":{"a":0,"k":100,"ix":7},"sk":{"a":0,"k":0,"ix":4},"sa":{"a":0,"k":0,"ix":5},"nm":"Transform"}],"nm":"组 1","np":2,"cix":2,"bm":0,"ix":1,"mn":"ADBE Vector Group","hd":false}],"ip":10.01001001001,"op":510.510510510511,"st":10.01001001001,"bm":0},{"ddd":0,"ind":2,"ty":4,"nm":"“图层 2”轮廓","sr":1,"ks":{"o":{"a":0,"k":100,"ix":11},"r":{"a":0,"k":0,"ix":10},"p":{"a":0,"k":[1249.252,508.352,0],"ix":2,"l":2},"a":{"a":0,"k":[-0.422,8.754,0],"ix":1,"l":2},"s":{"a":1,"k":[{"i":{"x":[0.238,0.667,0.667],"y":[1,1,1]},"o":{"x":[0.81,0.333,0.333],"y":[0,0,0]},"t":15.015,"s":[0,100,100]},{"t":23.3566900233567,"s":[100,100,100]}],"ix":6,"l":2}},"ao":0,"shapes":[{"ty":"gr","it":[{"ind":0,"ty":"sh","ix":1,"ks":{"a":0,"k":{"i":[[0,0],[0,0],[0,0],[0,0]],"o":[[0,0],[0,0],[0,0],[0,0]],"v":[[20.828,8.504],[-20.828,8.504],[-20.828,-8.504],[20.828,-8.504]],"c":true},"ix":2},"nm":"路径 1","mn":"ADBE Vector Shape - Group","hd":false},{"ty":"fl","c":{"a":0,"k":[0.092948442347,0.468252413881,1,1],"ix":4},"o":{"a":0,"k":100,"ix":5},"r":1,"bm":0,"nm":"填充 1","mn":"ADBE Vector Graphic - Fill","hd":false},{"ty":"tr","p":{"a":0,"k":[21.078,8.754],"ix":2},"a":{"a":0,"k":[0,0],"ix":1},"s":{"a":0,"k":[100,100],"ix":3},"r":{"a":0,"k":0,"ix":6},"o":{"a":0,"k":100,"ix":7},"sk":{"a":0,"k":0,"ix":4},"sa":{"a":0,"k":0,"ix":5},"nm":"Transform"}],"nm":"组 1","np":2,"cix":2,"bm":0,"ix":1,"mn":"ADBE Vector Group","hd":false}],"ip":10.01001001001,"op":510.510510510511,"st":10.01001001001,"bm":0},{"ddd":0,"ind":3,"ty":4,"nm":"“图层 5”轮廓","sr":1,"ks":{"o":{"a":0,"k":100,"ix":11},"r":{"a":0,"k":0,"ix":10},"p":{"a":0,"k":[750.661,508.487,0],"ix":2,"l":2},"a":{"a":0,"k":[69.713,81.308,0],"ix":1,"l":2},"s":{"a":0,"k":[100,100,100],"ix":6,"l":2}},"ao":0,"shapes":[{"ty":"gr","it":[{"ind":0,"ty":"sh","ix":1,"ks":{"a":0,"k":{"i":[[0,0],[0,0],[-5.09,-8.897],[5.329,-9.065],[13.619,0],[0.13,0.002],[0,0]],"o":[[0,0],[13.03,0],[4.89,8.548],[-5.193,8.833],[-0.129,0],[0,0],[0,0]],"v":[[-34.634,-65.256],[7.78,-65.256],[35.88,-51.186],[35.415,-22.153],[10.458,-8.53],[10.068,-8.533],[-34.634,-8.533]],"c":true},"ix":2},"nm":"路径 1","mn":"ADBE Vector Shape - Group","hd":false},{"ind":1,"ty":"sh","ix":2,"ks":{"a":0,"k":{"i":[[0.204,0.2],[0,0],[-8.397,3.766],[-4.264,8.227],[0,5.385],[8.251,8.386],[14.358,0],[0,0],[0,0],[0,0],[0,0],[0,0],[0,0],[0,0],[0,0],[0,0],[0,0],[0,0],[0,0],[0,0],[0,0],[0,0],[0,0],[0,0]],"o":[[0,0],[4.756,-0.025],[8.65,-4.39],[4.333,-8.357],[0,-12.273],[-9.114,-8.309],[0,0],[0,0],[0,0],[0,0],[0,0],[0,0],[0,0],[0,0],[0,0],[0,0],[0,0],[0,0],[0,0],[0,0],[0,0],[0,0],[0,0],[-0.129,0]],"v":[[51.673,67.024],[12.1,7.192],[31.605,3.418],[51.474,-14.762],[56.716,-36.678],[43.518,-68.71],[8.637,-81.058],[-68.059,-81.058],[-68.059,-64.506],[-51.758,-64.506],[-51.758,67.223],[-69.463,67.223],[-69.463,81.058],[-18.087,81.058],[-18.087,67.223],[-34.634,67.223],[-34.634,7.437],[-6.94,7.437],[31.835,67.223],[14.16,67.223],[14.16,81.058],[69.463,81.058],[69.463,67.223],[52.224,67.223]],"c":true},"ix":2},"nm":"路径 2","mn":"ADBE Vector Shape - Group","hd":false},{"ty":"mm","mm":1,"nm":"合并路径 1","mn":"ADBE Vector Filter - Merge","hd":false},{"ty":"fl","c":{"a":0,"k":[0,0,0,1],"ix":4},"o":{"a":0,"k":100,"ix":5},"r":1,"bm":0,"nm":"填充 1","mn":"ADBE Vector Graphic - Fill","hd":false},{"ty":"tr","p":{"a":0,"k":[69.713,81.309],"ix":2},"a":{"a":0,"k":[0,0],"ix":1},"s":{"a":0,"k":[100,100],"ix":3},"r":{"a":0,"k":0,"ix":6},"o":{"a":0,"k":100,"ix":7},"sk":{"a":0,"k":0,"ix":4},"sa":{"a":0,"k":0,"ix":5},"nm":"Transform"}],"nm":"组 1","np":4,"cix":2,"bm":0,"ix":1,"mn":"ADBE Vector Group","hd":false}],"ip":0,"op":500.5005005005,"st":0,"bm":0},{"ddd":0,"ind":4,"ty":4,"nm":"“图层 6”轮廓","sr":1,"ks":{"o":{"a":0,"k":100,"ix":11},"r":{"a":0,"k":0,"ix":10},"p":{"a":0,"k":[897.682,507.938,0],"ix":2,"l":2},"a":{"a":0,"k":[60.789,82.278,0],"ix":1,"l":2},"s":{"a":0,"k":[100,100,100],"ix":6,"l":2}},"ao":0,"shapes":[{"ty":"gr","it":[{"ind":0,"ty":"sh","ix":1,"ks":{"a":0,"k":{"i":[[2.862,3.746],[16.186,4.367],[2.025,0.5],[0.253,18.171],[-1.157,2.566],[-2.147,2.132],[-11.54,0],[0,0],[-8.123,-3.74],[-5.534,-5.941],[0,0],[0,0],[0,0],[0,0],[0,0],[0,0],[0.13,-0.054],[0.166,0.164],[7.107,2.48],[8.773,0.213],[6.409,-2.149],[4.781,-3.86],[2.586,-5.469],[0,-5.643],[-0.86,-3.017],[-2.344,-3.696],[-16.244,-4.449],[0,0],[-1.047,-0.291],[-1.103,-0.292],[0,0],[-10.302,-4.364],[-2.654,-3.269],[-0.712,-3.916],[1.31,-3.908],[3.499,-3.501],[4.866,-1.613],[5.06,-0.233],[1.033,0],[2.093,0.625],[0.735,0.262],[0,0],[1.454,0.641],[5.406,5.266],[0,0],[0.861,0.974],[0.217,0.253],[0.36,0.457],[0,0.215],[0,0],[0,0],[0,0],[0,0],[0,0],[0,0],[-8.248,-3.072],[-9.4,-0.208],[0,0],[-14.884,12.498],[-2.53,4.826],[-0.682,5.139],[1.122,4.756]],"o":[[-9.139,-13.78],[-1.844,-0.484],[-17.555,-4.341],[0,-2.726],[1.135,-2.527],[6.539,-6.495],[0,0],[8.053,0.069],[7.885,3.629],[0,0],[0,0],[0,0],[0,0],[0,0],[0,0],[0,0.154],[-0.106,0.042],[-6.467,-4.831],[-7.482,-2.61],[-9.47,0],[-5.304,1.778],[-4.63,3.592],[-2.482,5.25],[0,3.962],[0.93,3.262],[9.088,14.161],[0,0],[1.118,0.306],[1.158,0.314],[0,0],[6.815,1.798],[4.091,1.853],[2.595,3.2],[0.716,3.94],[-1.396,4.158],[-3.407,3.109],[-4.17,1.384],[-0.98,0.047],[-9.846,0],[-0.735,-0.234],[0,0],[-1.483,-0.533],[-7.242,-3.194],[0,0],[-0.884,-0.875],[-0.22,-0.251],[-0.381,-0.447],[-0.233,-0.349],[0,0],[0,0],[0,0],[0,0],[0,0],[0,0],[5.281,4.872],[8.734,3.251],[0,0],[7.993,0],[4.085,-3.527],[2.411,-4.598],[0.671,-5.076],[-1.152,-4.881]],"v":[[53.141,14.448],[5.248,-11.097],[-0.532,-12.552],[-40.187,-40.466],[-38.445,-48.44],[-33.496,-55.462],[-5.048,-65.682],[-4.679,-65.681],[20.048,-59.858],[40.558,-45.232],[40.843,-28.551],[40.852,-28.362],[55.329,-28.362],[55.329,-78.596],[40.842,-78.596],[40.842,-67.206],[40.619,-66.788],[40.22,-66.967],[20.048,-77.833],[-4.105,-82.028],[-27.704,-78.834],[-42.286,-70.681],[-53.314,-56.832],[-57.108,-40.18],[-55.864,-30.089],[-51.064,-19.89],[-3.483,4.813],[-3.108,4.916],[0.121,5.805],[3.517,6.711],[3.842,6.797],[27.397,14.658],[37.705,22.488],[42.759,33.364],[41.865,45.19],[34.486,56.735],[22.019,63.852],[8.11,66.288],[5.077,66.358],[-14.471,63.691],[-16.686,62.944],[-16.803,62.902],[-21.221,61.137],[-40.553,48.206],[-40.837,47.931],[-43.467,45.144],[-44.122,44.39],[-45.241,43.037],[-45.764,42.036],[-45.908,27.693],[-45.916,27.503],[-60.54,27.503],[-60.54,80.025],[-45.906,80.025],[-45.906,64.606],[-25.244,76.74],[2.473,82.028],[3.639,82.028],[45.238,69.53],[55.207,56.942],[59.868,42.267],[59.189,27.45]],"c":true},"ix":2},"nm":"路径 1","mn":"ADBE Vector Shape - Group","hd":false},{"ty":"fl","c":{"a":0,"k":[0,0,0,1],"ix":4},"o":{"a":0,"k":100,"ix":5},"r":1,"bm":0,"nm":"填充 1","mn":"ADBE Vector Graphic - Fill","hd":false},{"ty":"tr","p":{"a":0,"k":[60.789,82.278],"ix":2},"a":{"a":0,"k":[0,0],"ix":1},"s":{"a":0,"k":[100,100],"ix":3},"r":{"a":0,"k":0,"ix":6},"o":{"a":0,"k":100,"ix":7},"sk":{"a":0,"k":0,"ix":4},"sa":{"a":0,"k":0,"ix":5},"nm":"Transform"}],"nm":"组 1","np":2,"cix":2,"bm":0,"ix":1,"mn":"ADBE Vector Group","hd":false}],"ip":0,"op":500.5005005005,"st":0,"bm":0},{"ddd":0,"ind":5,"ty":4,"nm":"“图层 7”轮廓","sr":1,"ks":{"o":{"a":0,"k":100,"ix":11},"r":{"a":0,"k":0,"ix":10},"p":{"a":0,"k":[1040.693,507.939,0],"ix":2,"l":2},"a":{"a":0,"k":[60.717,82.277,0],"ix":1,"l":2},"s":{"a":0,"k":[100,100,100],"ix":6,"l":2}},"ao":0,"shapes":[{"ty":"gr","it":[{"ind":0,"ty":"sh","ix":1,"ks":{"a":0,"k":{"i":[[2.857,3.738],[16.097,4.342],[2.071,0.517],[0,0],[7.659,4.18],[0,8.01],[-0.255,1.295],[0,0],[-0.181,0.583],[-0.027,0.08],[0,0],[-2.632,2.641],[-11.588,0],[0,0],[-8.145,-3.741],[-5.608,-5.946],[0,0],[0,0],[0,0],[0,0],[0,0],[0,0],[0.132,-0.054],[0.088,0.085],[7.109,2.481],[8.772,0.212],[6.43,-2.149],[4.768,-3.848],[2.586,-5.469],[0,-5.644],[-0.872,-3.004],[-2.41,-3.685],[-0.205,-0.276],[-0.1,-0.141],[0,0],[-15.465,-4.26],[0,0],[-1.109,-0.312],[-1.204,-0.318],[-10.304,-4.364],[-2.674,-3.286],[-0.717,-3.884],[1.301,-3.917],[3.476,-3.511],[4.873,-1.629],[5.042,-0.254],[5.003,1.517],[7.308,9.205],[0,0.217],[0,0],[0,0],[0,0],[0,0],[0,0],[0,0],[-8.246,-3.07],[-9.399,-0.208],[0,0],[-14.745,12.498],[-2.529,4.826],[-0.681,5.138],[1.122,4.755]],"o":[[-9.32,-13.832],[-1.872,-0.498],[0,0],[-8.671,-2.16],[-8.799,-4.803],[-0.014,-1.274],[0,0],[0.122,-0.572],[0.024,-0.08],[0,0],[1.051,-3.18],[6.505,-6.529],[0,0],[8.046,0.069],[7.89,3.623],[0,0],[0,0],[0,0],[0,0],[0,0],[0,0],[0,0.155],[-0.13,0.051],[-6.467,-4.832],[-7.482,-2.61],[-9.414,0],[-5.354,1.79],[-4.628,3.591],[-2.483,5.249],[0,3.976],[0.949,3.27],[0.189,0.298],[0.103,0.14],[0,0],[9.501,13.077],[0,0],[1.19,0.329],[1.271,0.345],[6.814,1.798],[4.135,1.872],[2.576,3.166],[0.725,3.925],[-1.388,4.162],[-3.44,3.11],[-4.172,1.396],[-8.884,0.455],[-12.329,-3.909],[-0.236,-0.354],[0,0],[0,0],[0,0],[0,0],[0,0],[0,0],[5.282,4.874],[8.735,3.252],[0,0],[8.034,0],[4.085,-3.527],[2.413,-4.6],[0.671,-5.076],[-1.152,-4.884]],"v":[[53.072,14.451],[5.178,-11.097],[-0.721,-12.6],[-0.88,-12.639],[-27.039,-21.428],[-40.116,-40.469],[-39.751,-44.342],[-39.707,-44.57],[-39.251,-46.312],[-39.173,-46.55],[-39.142,-46.636],[-33.591,-55.41],[-5.119,-65.683],[-4.75,-65.682],[19.997,-59.859],[40.627,-45.234],[40.771,-28.552],[40.779,-28.362],[55.259,-28.362],[55.259,-78.597],[40.77,-78.597],[40.77,-67.206],[40.546,-66.787],[40.149,-66.967],[19.976,-77.834],[-4.177,-82.027],[-27.722,-78.834],[-42.358,-70.682],[-53.384,-56.833],[-57.178,-40.18],[-55.917,-30.088],[-50.993,-19.893],[-50.386,-19.032],[-50.079,-18.613],[-49.953,-18.437],[-3.81,4.734],[-3.386,4.851],[0.05,5.804],[3.771,6.796],[27.324,14.658],[37.584,22.43],[42.618,33.205],[41.749,45.023],[34.415,56.59],[21.887,63.731],[8.001,66.217],[-14.4,63.69],[-45.306,43.047],[-45.835,42.036],[-45.98,27.692],[-45.988,27.503],[-60.467,27.503],[-60.467,80.024],[-45.979,80.024],[-45.979,64.605],[-25.316,76.739],[2.4,82.027],[3.572,82.027],[45.168,69.529],[55.136,56.942],[59.796,42.266],[59.117,27.451]],"c":true},"ix":2},"nm":"路径 1","mn":"ADBE Vector Shape - Group","hd":false},{"ty":"fl","c":{"a":0,"k":[0,0,0,1],"ix":4},"o":{"a":0,"k":100,"ix":5},"r":1,"bm":0,"nm":"填充 1","mn":"ADBE Vector Graphic - Fill","hd":false},{"ty":"tr","p":{"a":0,"k":[60.717,82.278],"ix":2},"a":{"a":0,"k":[0,0],"ix":1},"s":{"a":0,"k":[100,100],"ix":3},"r":{"a":0,"k":0,"ix":6},"o":{"a":0,"k":100,"ix":7},"sk":{"a":0,"k":0,"ix":4},"sa":{"a":0,"k":0,"ix":5},"nm":"Transform"}],"nm":"组 1","np":2,"cix":2,"bm":0,"ix":1,"mn":"ADBE Vector Group","hd":false}],"ip":0,"op":500.5005005005,"st":0,"bm":0},{"ddd":0,"ind":6,"ty":4,"nm":"“图层 4”轮廓","sr":1,"ks":{"o":{"a":0,"k":100,"ix":11},"r":{"a":0,"k":0,"ix":10},"p":{"a":0,"k":[1173.603,507.334,0],"ix":2,"l":2},"a":{"a":0,"k":[59.244,82.843,0],"ix":1,"l":2},"s":{"a":0,"k":[100,100,100],"ix":6,"l":2}},"ao":0,"shapes":[{"ty":"gr","it":[{"ind":0,"ty":"sh","ix":1,"ks":{"a":0,"k":{"i":[[0,30.371],[16.649,6.152],[0,12.558],[31.712,0],[12.553,-17.685],[0,0],[-18.103,0],[0,-17.813],[16.78,0],[0,0],[0,0],[0,0],[0.529,-19.607],[24.048,0],[12.817,13.712],[0,0],[0,0],[0,0],[-21.538,0]],"o":[[0,-19.863],[14.138,-7.432],[0,-28.963],[-17.31,0.128],[0,0],[7.003,-9.483],[22.99,0],[0,17.044],[0,0],[0,0],[0,0],[21.405,0],[-1.188,20.888],[-15.46,0],[0,0],[0,0],[0,0],[16.12,15.121],[33.165,0]],"v":[[58.995,34.28],[32.308,-6.088],[52.656,-38.252],[-3.367,-82.593],[-51.729,-59.013],[-38.515,-50.427],[-3.367,-67.215],[36.008,-40.048],[2.844,-13.52],[-20.017,-13.52],[-20.017,2.884],[4.164,2.884],[41.948,34.024],[-1.65,66.061],[-47.104,47.48],[-47.765,47.224],[-58.995,59.526],[-58.467,59.654],[-1.65,82.593]],"c":true},"ix":2},"nm":"路径 1","mn":"ADBE Vector Shape - Group","hd":false},{"ty":"fl","c":{"a":0,"k":[0,0,0,1],"ix":4},"o":{"a":0,"k":100,"ix":5},"r":1,"bm":0,"nm":"填充 1","mn":"ADBE Vector Graphic - Fill","hd":false},{"ty":"tr","p":{"a":0,"k":[59.244,82.844],"ix":2},"a":{"a":0,"k":[0,0],"ix":1},"s":{"a":0,"k":[100,100],"ix":3},"r":{"a":0,"k":0,"ix":6},"o":{"a":0,"k":100,"ix":7},"sk":{"a":0,"k":0,"ix":4},"sa":{"a":0,"k":0,"ix":5},"nm":"Transform"}],"nm":"组 1","np":2,"cix":2,"bm":0,"ix":1,"mn":"ADBE Vector Group","hd":false}],"ip":0,"op":500.5005005005,"st":0,"bm":0}]}],"layers":[{"ddd":0,"ind":2,"ty":0,"nm":"logo","refId":"comp_0","sr":1,"ks":{"o":{"a":1,"k":[{"i":{"x":[0.833],"y":[0.833]},"o":{"x":[0.167],"y":[0.167]},"t":160,"s":[0]},{"t":165,"s":[100]}],"ix":11},"r":{"a":0,"k":0,"ix":10},"p":{"a":0,"k":[960,540,0],"ix":2,"l":2},"a":{"a":0,"k":[960,540,0],"ix":1,"l":2},"s":{"a":1,"k":[{"i":{"x":[0.262,0.262,0.667],"y":[1,1,1]},"o":{"x":[0.724,0.724,0.333],"y":[0,0,0]},"t":178,"s":[60.926,60.926,100]},{"t":189,"s":[100,100,100]}],"ix":6,"l":2}},"ao":0,"w":1920,"h":1080,"ip":163,"op":663.5005005005,"st":163,"bm":0},{"ddd":0,"ind":3,"ty":4,"nm":"R 2","sr":1,"ks":{"o":{"a":1,"k":[{"i":{"x":[0.667],"y":[1]},"o":{"x":[1],"y":[0]},"t":155,"s":[100]},{"t":165,"s":[0]}],"ix":11},"r":{"a":0,"k":0,"ix":10},"p":{"a":1,"k":[{"i":{"x":0.103,"y":1},"o":{"x":0.774,"y":0},"t":149,"s":[856.199,697.885,0],"to":[-3.833,-29.5,0],"ti":[3.833,29.5,0]},{"t":168,"s":[833.199,520.885,0]}],"ix":2,"l":2},"a":{"a":0,"k":[622.401,540.003,0],"ix":1,"l":2},"s":{"a":0,"k":[50,50,100],"ix":6,"l":2}},"ao":0,"ef":[{"ty":5,"nm":"路径约束","np":5,"mn":"Pseudo/DUIK path v2","ix":1,"en":1,"ef":[{"ty":0,"nm":"Percent along path","mn":"Pseudo/DUIK path v2-0001","ix":1,"v":{"a":0,"k":72,"ix":1}},{"ty":0,"nm":"Path Offset","mn":"Pseudo/DUIK path v2-0002","ix":2,"v":{"a":0,"k":0,"ix":2}},{"ty":7,"nm":"Orientation","mn":"Pseudo/DUIK path v2-0003","ix":3,"v":{"a":0,"k":0,"ix":3}}]}],"shapes":[{"ty":"gr","it":[{"ind":0,"ty":"sh","ix":1,"ks":{"a":0,"k":{"i":[[6.133,-5.862],[12.12,0],[0,0],[0,0],[0,0],[-6.147,-5.862],[0,-11.112]],"o":[[-6.147,5.862],[0,0],[0,0],[0,0],[12.12,0],[6.133,5.862],[0,11.114]],"v":[[35.718,-16.076],[8.186,-7.24],[-41.365,-7.24],[-41.365,-75.369],[8.186,-75.369],[35.718,-66.528],[44.838,-41.302]],"c":true},"ix":2},"nm":"路径 1","mn":"ADBE Vector Shape - Group","hd":false},{"ind":1,"ty":"sh","ix":2,"ks":{"a":0,"k":{"i":[[0.556,0.612],[0,0],[-8.828,8.571],[0,17.441],[10.279,9.988],[18.558,0],[0,0],[0,0],[0,0],[0,0],[0,0],[0,0],[0,0],[0,0],[0,0],[0,0],[0,0],[0,0],[0,0],[0,0],[0,0],[0,0],[0,0]],"o":[[0,0],[15.093,-1.18],[10.279,-9.981],[0,-17.44],[-10.224,-9.925],[0,0],[0,0],[0,0],[0,0],[0,0],[0,0],[0,0],[0,0],[0,0],[0,0],[0,0],[0,0],[0,0],[0,0],[0,0],[0,0],[0,0],[-0.223,-0.153]],"v":[[59.076,74.28],[15.541,14.701],[51.568,0.025],[67.057,-41.302],[51.568,-82.635],[8.186,-97.589],[-84.33,-97.589],[-84.33,-75.369],[-63.583,-75.369],[-63.583,75.37],[-84.33,75.37],[-84.33,97.589],[-21.875,97.589],[-21.875,75.37],[-41.365,75.37],[-41.365,14.979],[-12.276,14.979],[31.641,75.37],[16.27,75.37],[16.27,97.589],[84.33,97.589],[84.33,75.37],[60.278,75.37]],"c":true},"ix":2},"nm":"路径 2","mn":"ADBE Vector Shape - Group","hd":false},{"ty":"mm","mm":1,"nm":"合并路径 1","mn":"ADBE Vector Filter - Merge","hd":false},{"ty":"fl","c":{"a":0,"k":[0,0,0,1],"ix":4},"o":{"a":0,"k":100,"ix":5},"r":1,"bm":0,"nm":"填充 1","mn":"ADBE Vector Graphic - Fill","hd":false},{"ty":"tr","p":{"a":0,"k":[622.401,540.003],"ix":2},"a":{"a":0,"k":[0,0],"ix":1},"s":{"a":0,"k":[100,100],"ix":3},"r":{"a":0,"k":0,"ix":6},"o":{"a":0,"k":100,"ix":7},"sk":{"a":0,"k":0,"ix":4},"sa":{"a":0,"k":0,"ix":5},"nm":"Transform"}],"nm":"组 7","np":4,"cix":2,"bm":0,"ix":1,"mn":"ADBE Vector Group","hd":false}],"ip":149,"op":168,"st":-20,"bm":0},{"ddd":0,"ind":4,"ty":4,"nm":"S4","sr":1,"ks":{"o":{"a":1,"k":[{"i":{"x":[0.667],"y":[1]},"o":{"x":[1],"y":[0]},"t":155,"s":[100]},{"t":165,"s":[0]}],"ix":11},"r":{"a":0,"k":0,"ix":10},"p":{"a":1,"k":[{"i":{"x":0.103,"y":1},"o":{"x":0.847,"y":0},"t":149,"s":[1124.549,499.882,0],"to":[-19.167,3.5,0],"ti":[19.167,-3.5,0]},{"t":168,"s":[1009.549,520.882,0]}],"ix":2,"l":2},"a":{"a":0,"k":[861.251,540,0],"ix":1,"l":2},"s":{"a":0,"k":[50,50,100],"ix":6,"l":2}},"ao":0,"ef":[{"ty":5,"nm":"路径约束","np":5,"mn":"Pseudo/DUIK path v2","ix":1,"en":1,"ef":[{"ty":0,"nm":"Percent along path","mn":"Pseudo/DUIK path v2-0001","ix":1,"v":{"a":0,"k":42,"ix":1}},{"ty":0,"nm":"Path Offset","mn":"Pseudo/DUIK path v2-0002","ix":2,"v":{"a":0,"k":0,"ix":2}},{"ty":7,"nm":"Orientation","mn":"Pseudo/DUIK path v2-0003","ix":3,"v":{"a":0,"k":0,"ix":3}}]}],"shapes":[{"ty":"gr","it":[{"ind":0,"ty":"sh","ix":1,"ks":{"a":0,"k":{"i":[[8.488,4.202],[20.42,5.592],[6.529,2.938],[3.382,4.098],[0,5.021],[-6.814,5.842],[-15.698,0],[-6.647,-2.716],[-8.383,-8.995],[0,0],[0,0],[0,0],[0,0],[0,0],[19.058,0],[10.801,-9.821],[0,-16.516],[-5.139,-6.925],[-8.494,-4.196],[-20.434,-5.597],[-6.543,-2.938],[-3.389,-4.098],[0,-5.029],[7.814,-6.258],[15.53,0],[13.203,8.655],[3.82,4.035],[0,0],[0,0],[0,0],[0,0],[0,0],[-19.809,0],[-12.12,10.203],[0,17.649],[5.14,6.932]],"o":[[-7.987,-3.952],[-19.337,-5.299],[-5.139,-2.286],[-3.057,-3.688],[0,-8.349],[7.043,-6.035],[8.293,0],[12.127,5.028],[0,0],[0,0],[0,0],[0,0],[0,0],[-16.419,-11.675],[-22.414,0],[-10.988,9.988],[0,8.953],[4.89,6.584],[7.974,3.945],[19.33,5.3],[5.139,2.286],[3.049,3.681],[0,10.001],[-8.189,6.571],[-15.788,0],[-4.959,-3.209],[0,0],[0,0],[0,0],[0,0],[0,0],[16.517,11.682],[23.004,0],[12.502,-10.515],[0,-9.467],[-4.89,-6.577]],"v":[[46.445,1.388],[4.23,-12.787],[-34.749,-25.198],[-47.598,-34.818],[-52.141,-47.758],[-42.014,-68.852],[-7.744,-77.951],[14.78,-73.852],[45.681,-52.717],[45.681,-32.172],[67.9,-32.172],[67.9,-94.307],[45.681,-94.307],[45.681,-82.583],[-7.744,-100.169],[-57.795,-85.375],[-74.353,-45.431],[-66.609,-21.496],[-46.446,-5.258],[-4.237,8.918],[34.749,21.33],[47.598,30.95],[52.133,43.889],[40.521,68.052],[4.772,77.951],[-38.916,64.914],[-52.141,54.002],[-52.141,30.997],[-74.353,30.997],[-74.353,93.794],[-52.141,93.794],[-52.141,82.57],[2.577,100.169],[55.516,84.792],[74.353,42.341],[66.608,17.628]],"c":true},"ix":2},"nm":"路径 1","mn":"ADBE Vector Shape - Group","hd":false},{"ty":"fl","c":{"a":0,"k":[0,0,0,1],"ix":4},"o":{"a":0,"k":100,"ix":5},"r":1,"bm":0,"nm":"填充 1","mn":"ADBE Vector Graphic - Fill","hd":false},{"ty":"tr","p":{"a":0,"k":[861.251,540],"ix":2},"a":{"a":0,"k":[0,0],"ix":1},"s":{"a":0,"k":[100,100],"ix":3},"r":{"a":0,"k":0,"ix":6},"o":{"a":0,"k":100,"ix":7},"sk":{"a":0,"k":0,"ix":4},"sa":{"a":0,"k":0,"ix":5},"nm":"Transform"}],"nm":"组 6","np":2,"cix":2,"bm":0,"ix":1,"mn":"ADBE Vector Group","hd":false}],"ip":149,"op":168,"st":-16,"bm":0},{"ddd":0,"ind":5,"ty":4,"nm":"S3","sr":1,"ks":{"o":{"a":1,"k":[{"i":{"x":[0.667],"y":[1]},"o":{"x":[1],"y":[0]},"t":155,"s":[100]},{"t":164,"s":[0]}],"ix":11},"r":{"a":0,"k":0,"ix":10},"p":{"a":1,"k":[{"i":{"x":0.14,"y":1},"o":{"x":0.847,"y":0},"t":149,"s":[662.922,613.882,0],"to":[43.167,-15.5,0],"ti":[-43.167,15.5,0]},{"t":168,"s":[921.922,520.882,0]}],"ix":2,"l":2},"a":{"a":0,"k":[1097.624,540,0],"ix":1,"l":2},"s":{"a":0,"k":[50,50,100],"ix":6,"l":2}},"ao":0,"ef":[{"ty":5,"nm":"路径约束","np":5,"mn":"Pseudo/DUIK path v2","ix":1,"en":1,"ef":[{"ty":0,"nm":"Percent along path","mn":"Pseudo/DUIK path v2-0001","ix":1,"v":{"a":0,"k":53,"ix":1}},{"ty":0,"nm":"Path Offset","mn":"Pseudo/DUIK path v2-0002","ix":2,"v":{"a":0,"k":0,"ix":2}},{"ty":7,"nm":"Orientation","mn":"Pseudo/DUIK path v2-0003","ix":3,"v":{"a":0,"k":0,"ix":3}}]}],"shapes":[{"ty":"gr","it":[{"ind":0,"ty":"sh","ix":1,"ks":{"a":0,"k":{"i":[[8.487,4.202],[20.421,5.592],[6.543,2.938],[3.397,4.105],[0,5.028],[-6.808,5.842],[-15.698,0],[-6.648,-2.716],[-8.389,-9.001],[0,0],[0,0],[0,0],[0,0],[0,0],[19.058,0],[10.794,-9.821],[0,-16.516],[-5.139,-6.925],[-8.48,-4.188],[-20.433,-5.597],[-6.536,-2.938],[-3.388,-4.098],[0,-5.022],[7.821,-6.265],[15.523,0],[13.21,8.655],[3.799,4.022],[0,0],[0,0],[0,0],[0,0],[0,0],[-19.81,0],[-12.119,10.203],[0,17.655],[5.14,6.932]],"o":[[-7.987,-3.952],[-19.329,-5.299],[-5.133,-2.279],[-3.049,-3.681],[0,-8.356],[7.042,-6.035],[8.293,0],[12.12,5.021],[0,0],[0,0],[0,0],[0,0],[0,0],[-16.419,-11.675],[-22.415,0],[-10.995,9.988],[0,8.953],[4.897,6.584],[7.974,3.945],[19.33,5.3],[5.139,2.286],[3.057,3.688],[0,9.994],[-8.188,6.571],[-15.787,0],[-4.974,-3.223],[0,0],[0,0],[0,0],[0,0],[0,0],[16.516,11.682],[23.004,0],[12.503,-10.508],[0,-9.467],[-4.89,-6.577]],"v":[[46.446,1.388],[4.236,-12.787],[-34.749,-25.198],[-47.599,-34.818],[-52.134,-47.758],[-42.014,-68.852],[-7.744,-77.951],[14.781,-73.852],[45.681,-52.717],[45.681,-32.172],[67.901,-32.172],[67.901,-94.307],[45.681,-94.307],[45.681,-82.583],[-7.744,-100.169],[-57.787,-85.375],[-74.352,-45.431],[-66.609,-21.496],[-46.446,-5.258],[-4.23,8.918],[34.75,21.33],[47.598,30.95],[52.141,43.889],[40.521,68.052],[4.778,77.951],[-38.916,64.914],[-52.134,54.002],[-52.134,30.997],[-74.352,30.997],[-74.352,93.794],[-52.134,93.794],[-52.134,82.57],[2.584,100.169],[55.516,84.792],[74.353,42.341],[66.609,17.628]],"c":true},"ix":2},"nm":"路径 1","mn":"ADBE Vector Shape - Group","hd":false},{"ty":"fl","c":{"a":0,"k":[0,0,0,1],"ix":4},"o":{"a":0,"k":100,"ix":5},"r":1,"bm":0,"nm":"填充 1","mn":"ADBE Vector Graphic - Fill","hd":false},{"ty":"tr","p":{"a":0,"k":[1097.624,540],"ix":2},"a":{"a":0,"k":[0,0],"ix":1},"s":{"a":0,"k":[100,100],"ix":3},"r":{"a":0,"k":0,"ix":6},"o":{"a":0,"k":100,"ix":7},"sk":{"a":0,"k":0,"ix":4},"sa":{"a":0,"k":0,"ix":5},"nm":"Transform"}],"nm":"组 5","np":2,"cix":2,"bm":0,"ix":1,"mn":"ADBE Vector Group","hd":false}],"ip":149,"op":168,"st":-12,"bm":0},{"ddd":0,"ind":6,"ty":4,"nm":"4","sr":1,"ks":{"o":{"a":1,"k":[{"i":{"x":[0.667],"y":[1]},"o":{"x":[1],"y":[0]},"t":155,"s":[100]},{"t":165,"s":[0]}],"ix":11},"r":{"a":0,"k":0,"ix":10},"p":{"a":1,"k":[{"i":{"x":0.134,"y":1},"o":{"x":0.815,"y":0},"t":149,"s":[1279.549,243.882,0],"to":[-31.667,46,0],"ti":[31.667,-46,0]},{"t":168,"s":[1089.549,519.882,0]}],"ix":2,"l":2},"a":{"a":0,"k":[1313.25,540,0],"ix":1,"l":2},"s":{"a":0,"k":[50,50,100],"ix":6,"l":2}},"ao":0,"ef":[{"ty":5,"nm":"路径约束","np":5,"mn":"Pseudo/DUIK path v2","ix":1,"en":1,"ef":[{"ty":0,"nm":"Percent along path","mn":"Pseudo/DUIK path v2-0001","ix":1,"v":{"a":0,"k":0,"ix":1}},{"ty":0,"nm":"Path Offset","mn":"Pseudo/DUIK path v2-0002","ix":2,"v":{"a":0,"k":0,"ix":2}},{"ty":7,"nm":"Orientation","mn":"Pseudo/DUIK path v2-0003","ix":3,"v":{"a":0,"k":0,"ix":3}}]}],"shapes":[{"ty":"gr","it":[{"ind":0,"ty":"sh","ix":1,"ks":{"a":0,"k":{"i":[[7.445,9.53],[5.528,3.057],[0,17.572],[12.002,10.522],[20.128,0],[10.147,-4.944],[7.995,-6.897],[0,0],[0,0],[0,0],[-8.161,3.73],[-8.703,0],[-7.946,-6.313],[0,-9.294],[6.322,-5.487],[11.564,0],[0,0],[0,0],[0,0],[-6.772,-6.126],[0,-11.203],[7.863,-6.445],[15.247,0],[8.987,3.591],[7.043,7.307],[0,0],[0,0],[0,0],[-25.441,0],[-12.509,10.391],[0,17.816]],"o":[[-3.834,-4.91],[13.37,-8.876],[0,-15.697],[-11.725,-10.273],[-12.933,0],[-9.737,4.73],[0,0],[0,0],[0,0],[6.146,-5.348],[7.891,-3.597],[13.732,0],[7.543,6.008],[0,9.417],[-6.521,5.675],[0,0],[0,0],[0,0],[11.321,0],[6.564,5.939],[0,11.071],[-8.174,6.702],[-9.529,0],[-8.877,-3.557],[0,0],[0,0],[0,0],[18.794,18.275],[20.574,0],[12.843,-10.863],[0,-13.468]],"v":[[57.462,6.646],[43.375,-5.349],[63.51,-45.174],[45.424,-84.695],[-2.583,-100.169],[-37.368,-92.724],[-64.088,-75.201],[-65.755,-73.755],[-50.641,-57.37],[-49.161,-58.85],[-27.595,-72.534],[-2.583,-77.951],[30.082,-68.428],[41.292,-45.688],[31.901,-23.531],[4.647,-14.982],[-23.025,-14.982],[-23.025,7.237],[9.807,7.237],[36.7,16.343],[46.459,41.819],[34.776,67.844],[-0.515,77.951],[-28.422,72.534],[-52.218,56.343],[-53.78,55.043],[-68.678,71.185],[-67.185,72.63],[-0.515,100.169],[49.328,84.521],[68.678,41.306]],"c":true},"ix":2},"nm":"路径 1","mn":"ADBE Vector Shape - Group","hd":false},{"ty":"fl","c":{"a":0,"k":[0,0,0,1],"ix":4},"o":{"a":0,"k":100,"ix":5},"r":1,"bm":0,"nm":"填充 1","mn":"ADBE Vector Graphic - Fill","hd":false},{"ty":"tr","p":{"a":0,"k":[1313.25,540],"ix":2},"a":{"a":0,"k":[0,0],"ix":1},"s":{"a":0,"k":[100,100],"ix":3},"r":{"a":0,"k":0,"ix":6},"o":{"a":0,"k":100,"ix":7},"sk":{"a":0,"k":0,"ix":4},"sa":{"a":0,"k":0,"ix":5},"nm":"Transform"}],"nm":"组 4","np":2,"cix":2,"bm":0,"ix":1,"mn":"ADBE Vector Group","hd":false}],"ip":149,"op":168,"st":-8,"bm":0},{"ddd":0,"ind":7,"ty":4,"nm":"R","sr":1,"ks":{"o":{"a":0,"k":100,"ix":11},"r":{"a":0,"k":0,"ix":10},"p":{"a":0,"k":[-7.301,6.885,0],"ix":2,"x":"var $bm_rt;\nvar fx = effect('\\u8def\\u5f84\\u7ea6\\u675f');\nvar l = thisComp.layer('\\u8def\\u5f84\\u7ea6\\u675f');\nvar p = thisComp.layer('\\u8def\\u5f84\\u7ea6\\u675f')('ADBE Root Vectors Group')('\\u5f62\\u72b6 1')('ADBE Vectors Group')('\\u8def\\u5f84 1')(2);\nvar percent = $bm_div($bm_mod(fx(1).value, 100), 100);\nif (percent == 0)\n    percent = 0.0001;\nvar pathOffset = fx(2).value;\nvar result = l.toWorld($bm_sum(p.pointOnPath(percent, time), $bm_mul(p.normalOnPath(percent, time), pathOffset)));\nif (hasParent)\n    result = parent.fromWorld(result);\n$bm_rt = result = $bm_sum(result, value);","l":2},"a":{"a":0,"k":[622.401,540.003,0],"ix":1,"l":2},"s":{"a":0,"k":[50,50,100],"ix":6,"l":2}},"ao":0,"ef":[{"ty":5,"nm":"路径约束","np":5,"mn":"Pseudo/DUIK path v2","ix":1,"en":1,"ef":[{"ty":0,"nm":"Percent along path","mn":"Pseudo/DUIK path v2-0001","ix":1,"v":{"a":0,"k":72,"ix":1}},{"ty":0,"nm":"Path Offset","mn":"Pseudo/DUIK path v2-0002","ix":2,"v":{"a":0,"k":0,"ix":2}},{"ty":7,"nm":"Orientation","mn":"Pseudo/DUIK path v2-0003","ix":3,"v":{"a":0,"k":0,"ix":3}}]}],"shapes":[{"ty":"gr","it":[{"ind":0,"ty":"sh","ix":1,"ks":{"a":0,"k":{"i":[[6.133,-5.862],[12.12,0],[0,0],[0,0],[0,0],[-6.147,-5.862],[0,-11.112]],"o":[[-6.147,5.862],[0,0],[0,0],[0,0],[12.12,0],[6.133,5.862],[0,11.114]],"v":[[35.718,-16.076],[8.186,-7.24],[-41.365,-7.24],[-41.365,-75.369],[8.186,-75.369],[35.718,-66.528],[44.838,-41.302]],"c":true},"ix":2},"nm":"路径 1","mn":"ADBE Vector Shape - Group","hd":false},{"ind":1,"ty":"sh","ix":2,"ks":{"a":0,"k":{"i":[[0.556,0.612],[0,0],[-8.828,8.571],[0,17.441],[10.279,9.988],[18.558,0],[0,0],[0,0],[0,0],[0,0],[0,0],[0,0],[0,0],[0,0],[0,0],[0,0],[0,0],[0,0],[0,0],[0,0],[0,0],[0,0],[0,0]],"o":[[0,0],[15.093,-1.18],[10.279,-9.981],[0,-17.44],[-10.224,-9.925],[0,0],[0,0],[0,0],[0,0],[0,0],[0,0],[0,0],[0,0],[0,0],[0,0],[0,0],[0,0],[0,0],[0,0],[0,0],[0,0],[0,0],[-0.223,-0.153]],"v":[[59.076,74.28],[15.541,14.701],[51.568,0.025],[67.057,-41.302],[51.568,-82.635],[8.186,-97.589],[-84.33,-97.589],[-84.33,-75.369],[-63.583,-75.369],[-63.583,75.37],[-84.33,75.37],[-84.33,97.589],[-21.875,97.589],[-21.875,75.37],[-41.365,75.37],[-41.365,14.979],[-12.276,14.979],[31.641,75.37],[16.27,75.37],[16.27,97.589],[84.33,97.589],[84.33,75.37],[60.278,75.37]],"c":true},"ix":2},"nm":"路径 2","mn":"ADBE Vector Shape - Group","hd":false},{"ty":"mm","mm":1,"nm":"合并路径 1","mn":"ADBE Vector Filter - Merge","hd":false},{"ty":"fl","c":{"a":0,"k":[0,0,0,1],"ix":4},"o":{"a":0,"k":100,"ix":5},"r":1,"bm":0,"nm":"填充 1","mn":"ADBE Vector Graphic - Fill","hd":false},{"ty":"tr","p":{"a":0,"k":[622.401,540.003],"ix":2},"a":{"a":0,"k":[0,0],"ix":1},"s":{"a":0,"k":[100,100],"ix":3},"r":{"a":0,"k":0,"ix":6},"o":{"a":0,"k":100,"ix":7},"sk":{"a":0,"k":0,"ix":4},"sa":{"a":0,"k":0,"ix":5},"nm":"Transform"}],"nm":"组 7","np":4,"cix":2,"bm":0,"ix":1,"mn":"ADBE Vector Group","hd":false}],"ip":0,"op":149,"st":-20,"bm":0},{"ddd":0,"ind":8,"ty":4,"nm":"S1","sr":1,"ks":{"o":{"a":0,"k":100,"ix":11},"r":{"a":0,"k":0,"ix":10},"p":{"a":0,"k":[-10.451,3.882,0],"ix":2,"x":"var $bm_rt;\nvar fx = effect('\\u8def\\u5f84\\u7ea6\\u675f');\nvar l = thisComp.layer('\\u8def\\u5f84\\u7ea6\\u675f');\nvar p = thisComp.layer('\\u8def\\u5f84\\u7ea6\\u675f')('ADBE Root Vectors Group')('\\u5f62\\u72b6 1')('ADBE Vectors Group')('\\u8def\\u5f84 1')(2);\nvar percent = $bm_div($bm_mod(fx(1).value, 100), 100);\nif (percent == 0)\n    percent = 0.0001;\nvar pathOffset = fx(2).value;\nvar result = l.toWorld($bm_sum(p.pointOnPath(percent, time), $bm_mul(p.normalOnPath(percent, time), pathOffset)));\nif (hasParent)\n    result = parent.fromWorld(result);\n$bm_rt = result = $bm_sum(result, value);","l":2},"a":{"a":0,"k":[861.251,540,0],"ix":1,"l":2},"s":{"a":0,"k":[50,50,100],"ix":6,"l":2}},"ao":0,"ef":[{"ty":5,"nm":"路径约束","np":5,"mn":"Pseudo/DUIK path v2","ix":1,"en":1,"ef":[{"ty":0,"nm":"Percent along path","mn":"Pseudo/DUIK path v2-0001","ix":1,"v":{"a":0,"k":42,"ix":1}},{"ty":0,"nm":"Path Offset","mn":"Pseudo/DUIK path v2-0002","ix":2,"v":{"a":0,"k":0,"ix":2}},{"ty":7,"nm":"Orientation","mn":"Pseudo/DUIK path v2-0003","ix":3,"v":{"a":0,"k":0,"ix":3}}]}],"shapes":[{"ty":"gr","it":[{"ind":0,"ty":"sh","ix":1,"ks":{"a":0,"k":{"i":[[8.488,4.202],[20.42,5.592],[6.529,2.938],[3.382,4.098],[0,5.021],[-6.814,5.842],[-15.698,0],[-6.647,-2.716],[-8.383,-8.995],[0,0],[0,0],[0,0],[0,0],[0,0],[19.058,0],[10.801,-9.821],[0,-16.516],[-5.139,-6.925],[-8.494,-4.196],[-20.434,-5.597],[-6.543,-2.938],[-3.389,-4.098],[0,-5.029],[7.814,-6.258],[15.53,0],[13.203,8.655],[3.82,4.035],[0,0],[0,0],[0,0],[0,0],[0,0],[-19.809,0],[-12.12,10.203],[0,17.649],[5.14,6.932]],"o":[[-7.987,-3.952],[-19.337,-5.299],[-5.139,-2.286],[-3.057,-3.688],[0,-8.349],[7.043,-6.035],[8.293,0],[12.127,5.028],[0,0],[0,0],[0,0],[0,0],[0,0],[-16.419,-11.675],[-22.414,0],[-10.988,9.988],[0,8.953],[4.89,6.584],[7.974,3.945],[19.33,5.3],[5.139,2.286],[3.049,3.681],[0,10.001],[-8.189,6.571],[-15.788,0],[-4.959,-3.209],[0,0],[0,0],[0,0],[0,0],[0,0],[16.517,11.682],[23.004,0],[12.502,-10.515],[0,-9.467],[-4.89,-6.577]],"v":[[46.445,1.388],[4.23,-12.787],[-34.749,-25.198],[-47.598,-34.818],[-52.141,-47.758],[-42.014,-68.852],[-7.744,-77.951],[14.78,-73.852],[45.681,-52.717],[45.681,-32.172],[67.9,-32.172],[67.9,-94.307],[45.681,-94.307],[45.681,-82.583],[-7.744,-100.169],[-57.795,-85.375],[-74.353,-45.431],[-66.609,-21.496],[-46.446,-5.258],[-4.237,8.918],[34.749,21.33],[47.598,30.95],[52.133,43.889],[40.521,68.052],[4.772,77.951],[-38.916,64.914],[-52.141,54.002],[-52.141,30.997],[-74.353,30.997],[-74.353,93.794],[-52.141,93.794],[-52.141,82.57],[2.577,100.169],[55.516,84.792],[74.353,42.341],[66.608,17.628]],"c":true},"ix":2},"nm":"路径 1","mn":"ADBE Vector Shape - Group","hd":false},{"ty":"fl","c":{"a":0,"k":[0,0,0,1],"ix":4},"o":{"a":0,"k":100,"ix":5},"r":1,"bm":0,"nm":"填充 1","mn":"ADBE Vector Graphic - Fill","hd":false},{"ty":"tr","p":{"a":0,"k":[861.251,540],"ix":2},"a":{"a":0,"k":[0,0],"ix":1},"s":{"a":0,"k":[100,100],"ix":3},"r":{"a":0,"k":0,"ix":6},"o":{"a":0,"k":100,"ix":7},"sk":{"a":0,"k":0,"ix":4},"sa":{"a":0,"k":0,"ix":5},"nm":"Transform"}],"nm":"组 6","np":2,"cix":2,"bm":0,"ix":1,"mn":"ADBE Vector Group","hd":false}],"ip":0,"op":149,"st":-16,"bm":0},{"ddd":0,"ind":9,"ty":4,"nm":"S2","sr":1,"ks":{"o":{"a":0,"k":100,"ix":11},"r":{"a":0,"k":0,"ix":10},"p":{"a":0,"k":[-12.078,4.882,0],"ix":2,"x":"var $bm_rt;\nvar fx = effect('\\u8def\\u5f84\\u7ea6\\u675f');\nvar l = thisComp.layer('\\u8def\\u5f84\\u7ea6\\u675f');\nvar p = thisComp.layer('\\u8def\\u5f84\\u7ea6\\u675f')('ADBE Root Vectors Group')('\\u5f62\\u72b6 1')('ADBE Vectors Group')('\\u8def\\u5f84 1')(2);\nvar percent = $bm_div($bm_mod(fx(1).value, 100), 100);\nif (percent == 0)\n    percent = 0.0001;\nvar pathOffset = fx(2).value;\nvar result = l.toWorld($bm_sum(p.pointOnPath(percent, time), $bm_mul(p.normalOnPath(percent, time), pathOffset)));\nif (hasParent)\n    result = parent.fromWorld(result);\n$bm_rt = result = $bm_sum(result, value);","l":2},"a":{"a":0,"k":[1097.624,540,0],"ix":1,"l":2},"s":{"a":0,"k":[50,50,100],"ix":6,"l":2}},"ao":0,"ef":[{"ty":5,"nm":"路径约束","np":5,"mn":"Pseudo/DUIK path v2","ix":1,"en":1,"ef":[{"ty":0,"nm":"Percent along path","mn":"Pseudo/DUIK path v2-0001","ix":1,"v":{"a":0,"k":53,"ix":1}},{"ty":0,"nm":"Path Offset","mn":"Pseudo/DUIK path v2-0002","ix":2,"v":{"a":0,"k":0,"ix":2}},{"ty":7,"nm":"Orientation","mn":"Pseudo/DUIK path v2-0003","ix":3,"v":{"a":0,"k":0,"ix":3}}]}],"shapes":[{"ty":"gr","it":[{"ind":0,"ty":"sh","ix":1,"ks":{"a":0,"k":{"i":[[8.487,4.202],[20.421,5.592],[6.543,2.938],[3.397,4.105],[0,5.028],[-6.808,5.842],[-15.698,0],[-6.648,-2.716],[-8.389,-9.001],[0,0],[0,0],[0,0],[0,0],[0,0],[19.058,0],[10.794,-9.821],[0,-16.516],[-5.139,-6.925],[-8.48,-4.188],[-20.433,-5.597],[-6.536,-2.938],[-3.388,-4.098],[0,-5.022],[7.821,-6.265],[15.523,0],[13.21,8.655],[3.799,4.022],[0,0],[0,0],[0,0],[0,0],[0,0],[-19.81,0],[-12.119,10.203],[0,17.655],[5.14,6.932]],"o":[[-7.987,-3.952],[-19.329,-5.299],[-5.133,-2.279],[-3.049,-3.681],[0,-8.356],[7.042,-6.035],[8.293,0],[12.12,5.021],[0,0],[0,0],[0,0],[0,0],[0,0],[-16.419,-11.675],[-22.415,0],[-10.995,9.988],[0,8.953],[4.897,6.584],[7.974,3.945],[19.33,5.3],[5.139,2.286],[3.057,3.688],[0,9.994],[-8.188,6.571],[-15.787,0],[-4.974,-3.223],[0,0],[0,0],[0,0],[0,0],[0,0],[16.516,11.682],[23.004,0],[12.503,-10.508],[0,-9.467],[-4.89,-6.577]],"v":[[46.446,1.388],[4.236,-12.787],[-34.749,-25.198],[-47.599,-34.818],[-52.134,-47.758],[-42.014,-68.852],[-7.744,-77.951],[14.781,-73.852],[45.681,-52.717],[45.681,-32.172],[67.901,-32.172],[67.901,-94.307],[45.681,-94.307],[45.681,-82.583],[-7.744,-100.169],[-57.787,-85.375],[-74.352,-45.431],[-66.609,-21.496],[-46.446,-5.258],[-4.23,8.918],[34.75,21.33],[47.598,30.95],[52.141,43.889],[40.521,68.052],[4.778,77.951],[-38.916,64.914],[-52.134,54.002],[-52.134,30.997],[-74.352,30.997],[-74.352,93.794],[-52.134,93.794],[-52.134,82.57],[2.584,100.169],[55.516,84.792],[74.353,42.341],[66.609,17.628]],"c":true},"ix":2},"nm":"路径 1","mn":"ADBE Vector Shape - Group","hd":false},{"ty":"fl","c":{"a":0,"k":[0,0,0,1],"ix":4},"o":{"a":0,"k":100,"ix":5},"r":1,"bm":0,"nm":"填充 1","mn":"ADBE Vector Graphic - Fill","hd":false},{"ty":"tr","p":{"a":0,"k":[1097.624,540],"ix":2},"a":{"a":0,"k":[0,0],"ix":1},"s":{"a":0,"k":[100,100],"ix":3},"r":{"a":0,"k":0,"ix":6},"o":{"a":0,"k":100,"ix":7},"sk":{"a":0,"k":0,"ix":4},"sa":{"a":0,"k":0,"ix":5},"nm":"Transform"}],"nm":"组 5","np":2,"cix":2,"bm":0,"ix":1,"mn":"ADBE Vector Group","hd":false}],"ip":0,"op":149,"st":-12,"bm":0},{"ddd":0,"ind":10,"ty":4,"nm":"3","sr":1,"ks":{"o":{"a":0,"k":100,"ix":11},"r":{"a":0,"k":0,"ix":10},"p":{"a":0,"k":[-4.451,5.882,0],"ix":2,"x":"var $bm_rt;\nvar fx = effect('\\u8def\\u5f84\\u7ea6\\u675f');\nvar l = thisComp.layer('\\u8def\\u5f84\\u7ea6\\u675f');\nvar p = thisComp.layer('\\u8def\\u5f84\\u7ea6\\u675f')('ADBE Root Vectors Group')('\\u5f62\\u72b6 1')('ADBE Vectors Group')('\\u8def\\u5f84 1')(2);\nvar percent = $bm_div($bm_mod(fx(1).value, 100), 100);\nif (percent == 0)\n    percent = 0.0001;\nvar pathOffset = fx(2).value;\nvar result = l.toWorld($bm_sum(p.pointOnPath(percent, time), $bm_mul(p.normalOnPath(percent, time), pathOffset)));\nif (hasParent)\n    result = parent.fromWorld(result);\n$bm_rt = result = $bm_sum(result, value);","l":2},"a":{"a":0,"k":[1313.25,540,0],"ix":1,"l":2},"s":{"a":0,"k":[50,50,100],"ix":6,"l":2}},"ao":0,"ef":[{"ty":5,"nm":"路径约束","np":5,"mn":"Pseudo/DUIK path v2","ix":1,"en":1,"ef":[{"ty":0,"nm":"Percent along path","mn":"Pseudo/DUIK path v2-0001","ix":1,"v":{"a":0,"k":0,"ix":1}},{"ty":0,"nm":"Path Offset","mn":"Pseudo/DUIK path v2-0002","ix":2,"v":{"a":0,"k":0,"ix":2}},{"ty":7,"nm":"Orientation","mn":"Pseudo/DUIK path v2-0003","ix":3,"v":{"a":0,"k":0,"ix":3}}]}],"shapes":[{"ty":"gr","it":[{"ind":0,"ty":"sh","ix":1,"ks":{"a":0,"k":{"i":[[7.445,9.53],[5.528,3.057],[0,17.572],[12.002,10.522],[20.128,0],[10.147,-4.944],[7.995,-6.897],[0,0],[0,0],[0,0],[-8.161,3.73],[-8.703,0],[-7.946,-6.313],[0,-9.294],[6.322,-5.487],[11.564,0],[0,0],[0,0],[0,0],[-6.772,-6.126],[0,-11.203],[7.863,-6.445],[15.247,0],[8.987,3.591],[7.043,7.307],[0,0],[0,0],[0,0],[-25.441,0],[-12.509,10.391],[0,17.816]],"o":[[-3.834,-4.91],[13.37,-8.876],[0,-15.697],[-11.725,-10.273],[-12.933,0],[-9.737,4.73],[0,0],[0,0],[0,0],[6.146,-5.348],[7.891,-3.597],[13.732,0],[7.543,6.008],[0,9.417],[-6.521,5.675],[0,0],[0,0],[0,0],[11.321,0],[6.564,5.939],[0,11.071],[-8.174,6.702],[-9.529,0],[-8.877,-3.557],[0,0],[0,0],[0,0],[18.794,18.275],[20.574,0],[12.843,-10.863],[0,-13.468]],"v":[[57.462,6.646],[43.375,-5.349],[63.51,-45.174],[45.424,-84.695],[-2.583,-100.169],[-37.368,-92.724],[-64.088,-75.201],[-65.755,-73.755],[-50.641,-57.37],[-49.161,-58.85],[-27.595,-72.534],[-2.583,-77.951],[30.082,-68.428],[41.292,-45.688],[31.901,-23.531],[4.647,-14.982],[-23.025,-14.982],[-23.025,7.237],[9.807,7.237],[36.7,16.343],[46.459,41.819],[34.776,67.844],[-0.515,77.951],[-28.422,72.534],[-52.218,56.343],[-53.78,55.043],[-68.678,71.185],[-67.185,72.63],[-0.515,100.169],[49.328,84.521],[68.678,41.306]],"c":true},"ix":2},"nm":"路径 1","mn":"ADBE Vector Shape - Group","hd":false},{"ty":"fl","c":{"a":0,"k":[0,0,0,1],"ix":4},"o":{"a":0,"k":100,"ix":5},"r":1,"bm":0,"nm":"填充 1","mn":"ADBE Vector Graphic - Fill","hd":false},{"ty":"tr","p":{"a":0,"k":[1313.25,540],"ix":2},"a":{"a":0,"k":[0,0],"ix":1},"s":{"a":0,"k":[100,100],"ix":3},"r":{"a":0,"k":0,"ix":6},"o":{"a":0,"k":100,"ix":7},"sk":{"a":0,"k":0,"ix":4},"sa":{"a":0,"k":0,"ix":5},"nm":"Transform"}],"nm":"组 4","np":2,"cix":2,"bm":0,"ix":1,"mn":"ADBE Vector Group","hd":false}],"ip":0,"op":149,"st":-8,"bm":0},{"ddd":0,"ind":11,"ty":4,"nm":"3w","parent":10,"sr":1,"ks":{"o":{"a":0,"k":100,"ix":11},"r":{"a":0,"k":0,"ix":10},"p":{"a":0,"k":[1310.808,540.494,0],"ix":2,"l":2},"a":{"a":0,"k":[-413.971,336.247,0],"ix":1,"l":2},"s":{"a":0,"k":[180,180,100],"ix":6,"l":2}},"ao":0,"shapes":[{"ty":"gr","it":[{"d":1,"ty":"el","s":{"a":0,"k":[138.941,138.941],"ix":2},"p":{"a":0,"k":[0,0],"ix":3},"nm":"椭圆路径 1","mn":"ADBE Vector Shape - Ellipse","hd":false},{"ty":"fl","c":{"a":0,"k":[1,1,1,1],"ix":4},"o":{"a":0,"k":100,"ix":5},"r":1,"bm":0,"nm":"填充 1","mn":"ADBE Vector Graphic - Fill","hd":false},{"ty":"tr","p":{"a":0,"k":[-413.971,336.247],"ix":2},"a":{"a":0,"k":[0,0],"ix":1},"s":{"a":0,"k":[100,100],"ix":3},"r":{"a":0,"k":0,"ix":6},"o":{"a":0,"k":100,"ix":7},"sk":{"a":0,"k":0,"ix":4},"sa":{"a":0,"k":0,"ix":5},"nm":"Transform"}],"nm":"椭圆 1","np":3,"cix":2,"bm":0,"ix":1,"mn":"ADBE Vector Group","hd":false}],"ip":0,"op":150,"st":-150,"bm":0},{"ddd":0,"ind":12,"ty":4,"nm":"S1w","parent":8,"sr":1,"ks":{"o":{"a":0,"k":100,"ix":11},"r":{"a":0,"k":0,"ix":10},"p":{"a":0,"k":[859.509,541.402,0],"ix":2,"l":2},"a":{"a":0,"k":[-413.971,336.247,0],"ix":1,"l":2},"s":{"a":0,"k":[180,180,100],"ix":6,"l":2}},"ao":0,"shapes":[{"ty":"gr","it":[{"d":1,"ty":"el","s":{"a":0,"k":[138.941,138.941],"ix":2},"p":{"a":0,"k":[0,0],"ix":3},"nm":"椭圆路径 1","mn":"ADBE Vector Shape - Ellipse","hd":false},{"ty":"fl","c":{"a":0,"k":[1,1,1,1],"ix":4},"o":{"a":0,"k":100,"ix":5},"r":1,"bm":0,"nm":"填充 1","mn":"ADBE Vector Graphic - Fill","hd":false},{"ty":"tr","p":{"a":0,"k":[-413.971,336.247],"ix":2},"a":{"a":0,"k":[0,0],"ix":1},"s":{"a":0,"k":[100,100],"ix":3},"r":{"a":0,"k":0,"ix":6},"o":{"a":0,"k":100,"ix":7},"sk":{"a":0,"k":0,"ix":4},"sa":{"a":0,"k":0,"ix":5},"nm":"Transform"}],"nm":"椭圆 1","np":3,"cix":2,"bm":0,"ix":1,"mn":"ADBE Vector Group","hd":false}],"ip":0,"op":150,"st":-150,"bm":0},{"ddd":0,"ind":13,"ty":4,"nm":"S2w","parent":9,"sr":1,"ks":{"o":{"a":0,"k":100,"ix":11},"r":{"a":0,"k":0,"ix":10},"p":{"a":0,"k":[1091.117,539.071,0],"ix":2,"l":2},"a":{"a":0,"k":[-413.971,336.247,0],"ix":1,"l":2},"s":{"a":0,"k":[180,180,100],"ix":6,"l":2}},"ao":0,"shapes":[{"ty":"gr","it":[{"d":1,"ty":"el","s":{"a":0,"k":[138.941,138.941],"ix":2},"p":{"a":0,"k":[0,0],"ix":3},"nm":"椭圆路径 1","mn":"ADBE Vector Shape - Ellipse","hd":false},{"ty":"fl","c":{"a":0,"k":[1,1,1,1],"ix":4},"o":{"a":0,"k":100,"ix":5},"r":1,"bm":0,"nm":"填充 1","mn":"ADBE Vector Graphic - Fill","hd":false},{"ty":"tr","p":{"a":0,"k":[-413.971,336.247],"ix":2},"a":{"a":0,"k":[0,0],"ix":1},"s":{"a":0,"k":[100,100],"ix":3},"r":{"a":0,"k":0,"ix":6},"o":{"a":0,"k":100,"ix":7},"sk":{"a":0,"k":0,"ix":4},"sa":{"a":0,"k":0,"ix":5},"nm":"Transform"}],"nm":"椭圆 1","np":3,"cix":2,"bm":0,"ix":1,"mn":"ADBE Vector Group","hd":false}],"ip":0,"op":150,"st":-150,"bm":0},{"ddd":0,"ind":14,"ty":4,"nm":"Rw","parent":7,"sr":1,"ks":{"o":{"a":0,"k":100,"ix":11},"r":{"a":0,"k":0,"ix":10},"p":{"a":0,"k":[614.646,545.981,0],"ix":2,"l":2},"a":{"a":0,"k":[-413.971,336.247,0],"ix":1,"l":2},"s":{"a":0,"k":[190,190,100],"ix":6,"l":2}},"ao":0,"shapes":[{"ty":"gr","it":[{"d":1,"ty":"el","s":{"a":0,"k":[138.941,138.941],"ix":2},"p":{"a":0,"k":[0,0],"ix":3},"nm":"椭圆路径 1","mn":"ADBE Vector Shape - Ellipse","hd":false},{"ty":"fl","c":{"a":0,"k":[1,1,1,1],"ix":4},"o":{"a":0,"k":100,"ix":5},"r":1,"bm":0,"nm":"填充 1","mn":"ADBE Vector Graphic - Fill","hd":false},{"ty":"tr","p":{"a":0,"k":[-413.971,336.247],"ix":2},"a":{"a":0,"k":[0,0],"ix":1},"s":{"a":0,"k":[100,100],"ix":3},"r":{"a":0,"k":0,"ix":6},"o":{"a":0,"k":100,"ix":7},"sk":{"a":0,"k":0,"ix":4},"sa":{"a":0,"k":0,"ix":5},"nm":"Transform"}],"nm":"椭圆 1","np":3,"cix":2,"bm":0,"ix":1,"mn":"ADBE Vector Group","hd":false}],"ip":0,"op":150,"st":-150,"bm":0},{"ddd":0,"ind":15,"ty":4,"nm":"路径约束","sr":1,"ks":{"o":{"a":0,"k":100,"ix":11},"r":{"a":0,"k":0,"ix":10},"p":{"a":0,"k":[960,540,0],"ix":2,"l":2},"a":{"a":0,"k":[0,0,0],"ix":1,"l":2},"s":{"a":0,"k":[100,100,100],"ix":6,"l":2}},"ao":0,"shapes":[{"ty":"gr","it":[{"ind":0,"ty":"sh","ix":1,"ks":{"a":1,"k":[{"i":{"x":0.333,"y":1},"o":{"x":0.565,"y":0},"t":0,"s":[{"i":[[0,0],[0.128,-0.212],[-0.123,-0.099],[0.065,-0.051],[0.094,0.004],[0,0],[0,0],[0,0]],"o":[[0,0],[-0.128,0.212],[0.071,0.057],[-0.047,0.038],[0.005,0],[0,0],[0,0],[0,0]],"v":[[560.572,-476.035],[-96.878,-471.398],[595.581,-199.571],[759.827,-27.03],[523.447,423.901],[-503.27,375.748],[-579.792,-19.566],[-335.639,-155.832]],"c":true}]},{"i":{"x":0.333,"y":1},"o":{"x":1,"y":0},"t":25,"s":[{"i":[[0,0],[104,-172],[-100,-80],[52.367,-41.647],[76.179,3.386],[0,0],[0,0],[0,0]],"o":[[0,0],[-104,172],[57.678,46.143],[-38.425,30.558],[4,0],[0,0],[0,0],[0,0]],"v":[[308,-360],[-392,48],[256,148],[252.453,296.57],[76,344],[88,172],[-412,332],[-44,-20]],"c":true}]},{"i":{"x":0.333,"y":1},"o":{"x":0.673,"y":0},"t":41,"s":[{"i":[[0,0],[0,0],[-194,-102],[329.739,-43.122],[46,132],[-75.85,-39.329],[-177.211,-47.711],[0,0]],"o":[[0,0],[0,0],[-76,-16],[-194.453,25.43],[-57.565,-165.186],[108,56],[104,28],[0,0]],"v":[[256,-228],[-428,-172],[398,212],[-119.547,156.57],[-478,124],[-14,-138],[-280,358],[66,2]],"c":true}]},{"i":{"x":0.333,"y":1},"o":{"x":0.673,"y":0},"t":44,"s":[{"i":[[0,0],[0,0],[-194,-102],[329.739,-43.122],[46,132],[-75.85,-39.329],[-177.211,-47.711],[0,0]],"o":[[0,0],[0,0],[-76,-16],[-194.453,25.43],[-57.565,-165.186],[108,56],[104,28],[0,0]],"v":[[256,-228],[-428,-172],[398,212],[-119.547,156.57],[-478,124],[-14,-138],[-280,358],[66,2]],"c":true}]},{"i":{"x":0.333,"y":1},"o":{"x":0.673,"y":0},"t":60,"s":[{"i":[[0,0],[0,0],[0,0],[0,0],[-161.472,-67.28],[-30.803,-19.98],[0,0],[0,0]],"o":[[0,0],[0,0],[0,0],[0,0],[72,30],[74,48],[0,0],[0,0]],"v":[[436,-42],[136,-218],[-262,298],[-405.547,-339.43],[-200,-74],[-46,-202],[-232,136],[118,40]],"c":true}]},{"i":{"x":0.56,"y":1},"o":{"x":0.375,"y":0},"t":64,"s":[{"i":[[0,0],[0,0],[0,0],[0,0],[-161.472,-67.28],[-30.803,-19.98],[0,0],[0,0]],"o":[[0,0],[0,0],[0,0],[0,0],[72,30],[74,48],[0,0],[0,0]],"v":[[436,-42],[136,-218],[-262,298],[-405.547,-339.43],[-200,-74],[-46,-202],[-232,136],[118,40]],"c":true}]},{"i":{"x":0.333,"y":1},"o":{"x":0.673,"y":0},"t":78,"s":[{"i":[[0,0],[0,0],[0,0],[0,0],[0,0],[0,0],[-12,64],[-10,50]],"o":[[0,0],[0,0],[0,0],[0,0],[0,0],[0,0],[12,-64],[10,-50]],"v":[[224,-48],[40,-390],[-136,-374],[-377.547,-351.43],[220,130],[-462,304],[32,80],[-228,-18]],"c":true}]},{"i":{"x":0.553,"y":1},"o":{"x":0.467,"y":0},"t":81,"s":[{"i":[[0,0],[0,0],[0,0],[0,0],[0,0],[0,0],[-12,64],[-10,50]],"o":[[0,0],[0,0],[0,0],[0,0],[0,0],[0,0],[12,-64],[10,-50]],"v":[[224,-48],[40,-390],[-136,-374],[-377.547,-351.43],[220,130],[-462,304],[32,80],[-228,-18]],"c":true}]},{"i":{"x":0.333,"y":1},"o":{"x":0.673,"y":0},"t":95,"s":[{"i":[[0,0],[20,50],[191.871,-81.24],[-40.453,-52.57],[-166,-10],[0,0],[0,0],[-10,50]],"o":[[0,0],[-20,-50],[-112.19,47.502],[33.547,39.43],[166,10],[0,0],[0,0],[10,-50]],"v":[[-52,2],[412,-286],[-186,-104],[-491.547,96.57],[-100,96],[112,226],[342,-30],[-436,260]],"c":true}]},{"i":{"x":0.333,"y":1},"o":{"x":0.673,"y":0},"t":99,"s":[{"i":[[0,0],[20,50],[191.871,-81.24],[-40.453,-52.57],[-166,-10],[0,0],[0,0],[-10,50]],"o":[[0,0],[-20,-50],[-112.19,47.502],[33.547,39.43],[166,10],[0,0],[0,0],[10,-50]],"v":[[-52,2],[412,-286],[-186,-104],[-491.547,96.57],[-100,96],[112,226],[342,-30],[-436,260]],"c":true}]},{"t":119,"s":[{"i":[[0,0],[108,82],[169.482,72.635],[-544.453,-274.57],[272,-70],[0,0],[0,0],[0,0]],"o":[[0,0],[-111.514,-84.668],[-126,-54],[172.729,87.108],[-114.161,29.38],[0,0],[0,0],[0,0]],"v":[[122,84],[324,-302],[-264,-192],[422.453,-149.43],[38,-16],[-304,74],[40,-190],[-200,410]],"c":true}]}],"ix":2},"nm":"路径 1","mn":"ADBE Vector Shape - Group","hd":false},{"ty":"st","c":{"a":0,"k":[0.043137254902,0.439215686275,1,1],"ix":3},"o":{"a":0,"k":100,"ix":4},"w":{"a":0,"k":10,"ix":5},"lc":1,"lj":1,"ml":4,"bm":0,"nm":"描边 1","mn":"ADBE Vector Graphic - Stroke","hd":false},{"ty":"tr","p":{"a":0,"k":[0,0],"ix":2},"a":{"a":0,"k":[0,0],"ix":1},"s":{"a":0,"k":[100,100],"ix":3},"r":{"a":0,"k":0,"ix":6},"o":{"a":0,"k":100,"ix":7},"sk":{"a":0,"k":0,"ix":4},"sa":{"a":0,"k":0,"ix":5},"nm":"Transform"}],"nm":"形状 1","np":3,"cix":2,"bm":0,"ix":1,"mn":"ADBE Vector Group","hd":false},{"ty":"tm","s":{"a":0,"k":0,"ix":1},"e":{"a":1,"k":[{"i":{"x":[0.667],"y":[1]},"o":{"x":[0.333],"y":[0.571]},"t":4,"s":[0]},{"i":{"x":[0.833],"y":[1]},"o":{"x":[0.167],"y":[0]},"t":38,"s":[80]},{"i":{"x":[0.833],"y":[1]},"o":{"x":[0.167],"y":[0]},"t":87,"s":[85]},{"i":{"x":[0.833],"y":[1]},"o":{"x":[0.167],"y":[0]},"t":118,"s":[85]},{"t":149,"s":[0]}],"ix":2},"o":{"a":0,"k":0,"ix":3,"x":"var $bm_rt;\n$bm_rt = $bm_mul(time, 60);"},"m":1,"ix":2,"nm":"修剪路径 1","mn":"ADBE Vector Filter - Trim","hd":false}],"ip":0,"op":150,"st":0,"bm":0}],"markers":[]}